ff/__init__.py
ff/__main__.py
find_ff-610.data/scripts/ff
find_ff-610.dist-info/licenses/LICENSE
libff/__init__.py
libff/__version__.py
libff/argparse.py
libff/arguments.py
libff/attribute.py
libff/cache.py
libff/console.py
libff/context.py
libff/convert.py
libff/entry.py
libff/exceptions.py
libff/field.py
libff/filter.py
libff/find.py
libff/help.py
libff/ignore.py
libff/logger.py
libff/main.py
libff/parser.py
libff/path.py
libff/plugin.py
libff/processing.py
libff/registry.py
libff/type.py
libff/walk.py
libff/builtin/__init__.py
libff/builtin/file.py
libff/builtin/grep.py
libff/builtin/ignore.py
libff/builtin/media.py
libff/builtin/mime.py
usr/lib/ff/fs.py
usr/lib/ff/git.py
usr/lib/ff/hash.py
usr/lib/ff/introspect.py
usr/lib/ff/pacman.py
usr/lib/ff/tar.py
usr/lib/ff/xattr.py
usr/lib/python3.14/site-packages/libff/manpage.template
usr/share/ff/plugin_template.py
usr/share/man/man1/ff.1
usr/share/man/man7/ff.7
find_ff-610.dist-info/METADATA
find_ff-610.dist-info/WHEEL
find_ff-610.dist-info/top_level.txt
find_ff-610.dist-info/RECORD
